[
    {
        "versionCode": 5,
        "versionName": "1.0.5",
        "releaseDate": "2026-03-11",
        "releaseNotes": "\u2022 \u5386\u53f2\u53f7\u7801\u652f\u6301\u300c\u5728\u7ebf\u67e5\u8be2\u662f\u5426\u4e2d\u5956\u53ca\u91d1\u989d\u300d\uff0c\u5728\u5386\u53f2\u8bb0\u5f55\u5361\u7247\u5185\u8054\u5c55\u793a\u5956\u7ea7\u3001\u547d\u4e2d\u7403\u6570\u4e0e\u603b\u91d1\u989d\n\u2022 \u65b0\u589e\u67e5\u8be2\u670d\u52a1\u7aef\uff1a\u67e5\u8be2\u63a5\u53e3\u4e0e\u66f4\u65b0\u670d\u52a1\u4f7f\u7528\u72ec\u7acb\u670d\u52a1\u5668\u5730\u5740\uff0c\u652f\u6301\u5355\u72ec\u8c03\u8bd5\u3001\u5207\u6362\u73af\u5883\n\u2022 \u5173\u4e8e\u9875\u8c03\u8bd5\u9762\u677f\u6269\u5c55\uff1a\u53ef\u5206\u522b\u914d\u7f6e\u66f4\u65b0\u670d\u52a1\u5668\u4e0e\u67e5\u8be2\u670d\u52a1\u5668\u5730\u5740\uff0c\u5e76\u67e5\u770b\u5404\u81ea\u7684\u8fde\u901a\u6027\u65e5\u5fd7\n\u2022 \u63d0\u5347\u9632\u5446\u4f53\u9a8c\uff1a\u65e0\u671f\u53f7\u3001\u80c6\u62d6\u73a9\u6cd5\u6216\u7f51\u7edc\u5f02\u5e38\u7b49\u573a\u666f\u4e0b\u7ed9\u51fa\u6e05\u6670\u63d0\u793a\uff0c\u907f\u514d\u8bef\u89e6\u4e0e\u91cd\u590d\u8bf7\u6c42",
        "downloadUrl": "https://gitee.com/callmeleifengpleasse/zhongleme/releases/download/1.0.5/zhongleme.apk",
        "minVersionCode": 1
    },
    {
        "versionCode": 4,
        "versionName": "1.0.4",
        "releaseDate": "2026-03-07",
        "releaseNotes": "\u2022 \u5386\u53f2\u8bb0\u5f55\u4e2d\u5c55\u793a\u5f00\u5956\u65e5\u671f\n\u2022 \u5173\u4e8e\u9875\u9690\u85cf\u5165\u53e3\uff1a\u8fde\u7eed\u70b9\u51fb\u7248\u672c\u53f7 7 \u6b21\u53ef\u914d\u7f6e\u66f4\u65b0\u670d\u52a1\u5668\u5730\u5740\u5e76\u67e5\u770b\u8fde\u63a5\u65e5\u5fd7\n\u2022 \u66f4\u65b0\u670d\u52a1\u5668\u652f\u6301\u8fd0\u884c\u65f6\u914d\u7f6e\uff08DataStore \u6301\u4e45\u5316\uff09\u4e0e CLEARTEXT \u7f51\u7edc\u8bbf\u95ee\n\u2022 \u7248\u672c\u68c0\u6d4b\u4e0e\u54cd\u5e94\u4f53\u5f02\u5e38\u5904\u7406\u4f18\u5316\uff1bchangelog \u4e2d 1.0.4 \u7684 downloadUrl \u6307\u5411 /releases/1.0.4/zhongleme.apk",
        "downloadUrl": "https://gitee.com/callmeleifengpleasse/zhongleme/releases/download/1.0.4/zhongleme.apk",
        "minVersionCode": 1
    },
    {
        "versionCode": 3,
        "versionName": "1.0.3",
        "releaseDate": "2026-03-07",
        "releaseNotes": "\u2022 \u53f7\u7801\u751f\u6210\u540e\u65b0\u589e\u8d2d\u4e70\u6ce8\u6570\u4e0e\u5408\u8ba1\u91d1\u989d\u663e\u793a\n\u2022 \u65b0\u589e\u5f00\u5956\u65e5\u671f\u63d0\u793a\uff08\u7cbe\u786e\u5230\u4e0b\u6b21\u5f00\u5956\u65e5\uff09\n\u2022 \u652f\u6301\u666e\u901a\u3001\u590d\u5f0f\u3001\u80c6\u62d6\u4e09\u79cd\u73a9\u6cd5\u7684\u6ce8\u6570\u4e0e\u91d1\u989d\u8ba1\u7b97",
        "downloadUrl": "http://192.168.3.24:5000/releases/zhongleme.apk",
        "minVersionCode": 2
    },
    {
        "versionCode": 2,
        "versionName": "1.0.2",
        "releaseDate": "2026-03-07",
        "releaseNotes": "\u2022 \u53f7\u7801\u751f\u6210\u540e\u65b0\u589e\u8d2d\u4e70\u6ce8\u6570\u4e0e\u5408\u8ba1\u91d1\u989d\u663e\u793a\n\u2022 \u65b0\u589e\u5f00\u5956\u65e5\u671f\u63d0\u793a\uff08\u7cbe\u786e\u5230\u4e0b\u6b21\u5f00\u5956\u65e5\uff09\n\u2022 \u652f\u6301\u666e\u901a\u3001\u590d\u5f0f\u3001\u80c6\u62d6\u4e09\u79cd\u73a9\u6cd5\u7684\u6ce8\u6570\u4e0e\u91d1\u989d\u8ba1\u7b97",
        "downloadUrl": "",
        "minVersionCode": 1
    },
    {
        "versionCode": 1,
        "versionName": "1.0.0",
        "releaseDate": "2026-03-07",
        "releaseNotes": "\u66f4\u65b0\u5185\u5bb9",
        "downloadUrl": "",
        "minVersionCode": 1
    },
    {
        "versionCode": 1,
        "versionName": "1.0.0",
        "releaseDate": "2026-03-07",
        "releaseNotes": "\u9996\u6b21\u53d1\u5e03\u3002\n- \u53cc\u8272\u7403/\u5927\u4e50\u900f\u9009\u53f7\n- \u5386\u53f2\u8bb0\u5f55\u4e0e\u671f\u53f7\uff08\u542b\u6625\u8282\u4f11\u5e02\uff09\n- \u591a\u79cd\u4e3b\u9898\uff08Material\u3001\u9e3f\u8499\u3001iOS\uff09\n- \u5e94\u7528\u5185\u66f4\u65b0",
        "downloadUrl": "",
        "minVersionCode": 1
    }
]